{
    "os": "Linux-5.4.0-73-generic-x86_64-with-glibc2.10",
    "python": "3.8.5",
    "heartbeatAt": "2021-07-20T21:55:14.285050",
    "startedAt": "2021-07-20T21:55:13.579884",
    "docker": null,
    "gpu": "NVIDIA GeForce RTX 2080 Ti",
    "gpu_count": 1,
    "cpu_count": 12,
    "cuda": null,
    "args": [],
    "state": "running",
    "program": "main.py",
    "codePath": "main.py",
    "git": {
        "remote": "https://github.com/Flowerfan/SF-Net.git",
        "commit": "69e679991dbcac50630a5857f0eef98460e99e4e"
    },
    "email": null,
    "root": "/home/user/puri/repro/SF-Net",
    "host": "cuda9",
    "username": "puri",
    "executable": "/home/user/puri/miniconda3/bin/python"
}
